jsonish_py-0.0.1.dist-info/METADATA
jsonish_py-0.0.1.dist-info/WHEEL
jsonish_py/__init__.py
jsonish_py/_rust.cpython-313-darwin.so
jsonish_py/py.typed
jsonish_py-0.0.1.dist-info/RECORD
