Metadata-Version: 2.4
Name: jsonish_py
Version: 0.0.1
Requires-Dist: pydantic>=2.0.0
Requires-Dist: pytest>=8.4.1 ; extra == 'dev'
Provides-Extra: dev
Summary: Wrapper around `jsonish` from BAML
Author-email: Noam Finkelstein <noam.finkelstein@liquid.ai>
Requires-Python: >=3.10
